carpo/__init__.py
carpo/cli.py
carpo/record.py
carpo-0.4.dist-info/DESCRIPTION.rst
carpo-0.4.dist-info/METADATA
carpo-0.4.dist-info/RECORD
carpo-0.4.dist-info/WHEEL
carpo-0.4.dist-info/entry_points.txt
carpo-0.4.dist-info/metadata.json
carpo-0.4.dist-info/top_level.txt
