Metadata-Version: 2.0
Name: carpo
Version: 0.4
Summary: Run, profile, and save Jupyter notebooks from the command line
Home-page: https://github.com/ColCarroll/carpo
Author: Colin Carroll
Author-email: colcarroll@gmail.com
License: MIT
Platform: UNKNOWN
Classifier: Development Status :: 3 - Alpha
Classifier: Intended Audience :: Developers
Classifier: License :: OSI Approved :: MIT License
Classifier: Programming Language :: Python :: 2
Classifier: Programming Language :: Python :: 2.7
Classifier: Programming Language :: Python :: 3
Classifier: Programming Language :: Python :: 3.4
Classifier: Programming Language :: Python :: 3.5
Classifier: Programming Language :: Python :: 3.6
Requires-Dist: Click (>=6.7)
Requires-Dist: GitPython (>=2.1.3)
Requires-Dist: ipykernel
Requires-Dist: ipython
Requires-Dist: nbconvert (>=5.1.1)
Requires-Dist: nbformat (>=4.3.0)
Requires-Dist: terminaltables
